huaweicloudsdkeps/__init__.py
huaweicloudsdkeps/v1/__init__.py
huaweicloudsdkeps/v1/eps_async_client.py
huaweicloudsdkeps/v1/eps_client.py
huaweicloudsdkeps/v1/model/__init__.py
huaweicloudsdkeps/v1/model/associated_resource_list_response.py
huaweicloudsdkeps/v1/model/create_enterprise_project_request.py
huaweicloudsdkeps/v1/model/create_enterprise_project_response.py
huaweicloudsdkeps/v1/model/delete_enterprise_project_request.py
huaweicloudsdkeps/v1/model/delete_enterprise_project_response.py
huaweicloudsdkeps/v1/model/disable_action.py
huaweicloudsdkeps/v1/model/disable_enterprise_project_request.py
huaweicloudsdkeps/v1/model/disable_enterprise_project_response.py
huaweicloudsdkeps/v1/model/enable_action.py
huaweicloudsdkeps/v1/model/enable_enterprise_project_request.py
huaweicloudsdkeps/v1/model/enable_enterprise_project_response.py
huaweicloudsdkeps/v1/model/enterprise_project.py
huaweicloudsdkeps/v1/model/enterprise_project_config.py
huaweicloudsdkeps/v1/model/ep_detail.py
huaweicloudsdkeps/v1/model/ep_quotas.py
huaweicloudsdkeps/v1/model/errors.py
huaweicloudsdkeps/v1/model/link.py
huaweicloudsdkeps/v1/model/list_api_versions_request.py
huaweicloudsdkeps/v1/model/list_api_versions_response.py
huaweicloudsdkeps/v1/model/list_enterprise_project_request.py
huaweicloudsdkeps/v1/model/list_enterprise_project_response.py
huaweicloudsdkeps/v1/model/list_migration_record_request.py
huaweicloudsdkeps/v1/model/list_migration_record_response.py
huaweicloudsdkeps/v1/model/list_providers_request.py
huaweicloudsdkeps/v1/model/list_providers_response.py
huaweicloudsdkeps/v1/model/list_resource_mapping_request.py
huaweicloudsdkeps/v1/model/list_resource_mapping_response.py
huaweicloudsdkeps/v1/model/match.py
huaweicloudsdkeps/v1/model/migrate_resource.py
huaweicloudsdkeps/v1/model/migrate_resource_request.py
huaweicloudsdkeps/v1/model/migrate_resource_response.py
huaweicloudsdkeps/v1/model/provider_response_body.py
huaweicloudsdkeps/v1/model/quotas_detail.py
huaweicloudsdkeps-3.1.184.dist-info/METADATA
huaweicloudsdkeps-3.1.184.dist-info/WHEEL
huaweicloudsdkeps-3.1.184.dist-info/licenses/LICENSE
huaweicloudsdkeps-3.1.184.dist-info/RECORD
